necmec_api/__init__.py
necmec_api/api.py
necmec_api/cli.py
necmec_api-0.1.3.dist-info/licenses/LICENSE
necmec_api-0.1.3.dist-info/METADATA
necmec_api-0.1.3.dist-info/WHEEL
necmec_api-0.1.3.dist-info/entry_points.txt
necmec_api-0.1.3.dist-info/top_level.txt
necmec_api-0.1.3.dist-info/RECORD
