Metadata-Version: 2.4
Name: necmec_api
Version: 0.1.3
Summary: Python client for interacting with the necmec API
Home-page: https://github.com/bipulkkuri/necmec_api
Author: Bipul Kumar Kuri
License: MIT
Project-URL: Documentation, https://github.com/bipulkkuri/necmec_api
Project-URL: Bug Tracker, https://github.com/bipulkkuri/necmec_api/issues
Classifier: Programming Language :: Python :: 3
Classifier: License :: OSI Approved :: MIT License
Classifier: Operating System :: OS Independent
Requires-Python: >=3.6
License-File: LICENSE
Requires-Dist: requests>=2.25.1
Dynamic: author
Dynamic: classifier
Dynamic: description
Dynamic: description-content-type
Dynamic: home-page
Dynamic: license
Dynamic: license-file
Dynamic: project-url
Dynamic: requires-dist
Dynamic: requires-python
Dynamic: summary
